{
  "metadata": {
    "title": "نهج البلاغة",
    "author": "الإمام علي بن أبي طالب (ع)",
    "editor": "الشيخ محمد عبده",
    "work": "من كتاب له (ع) إلى أمراء البلاد في معنى الصلاة (الرسالة الثانية والخمسون)",
    "total_footnotes": 4,
    "total_sections": 1,
    "compiled_date": "2024-01-01",
    "categories": ["الصلاة", "أوقات الصلاة", "الإمامة", "الرعاية", "الفقه العملي"]
  },
  "content": {
    "sections": [
      {
        "id": 1,
        "text": "أمّا بعد ، فصلّوا بالنّاس الظّهر حتّى تفىء الشّمس من مربض العنز[1] ، وصلّوا بهم العصر والشّمس بيضاء حيّة فى عضو من النّهار حين يسار فيها فرسخان[2] وصلّوا بهم المغرب حين يفطر الصّائم ويدفع الحاجّ [إلى منى][3] وصلّوا بهم العشاء حين يتوارى الشّفق إلى ثلث اللّيل ، وصلّوا بهم الغداة والرّجل يعرف وجه صاحبه ، وصلّوا بهم صلاة أضعفهم ولا تكونوا فتّانين[4]",
        "footnotes": [
          {
            "id": 1,
            "text": "«تفىء» أي: تصل في ميلها جهة الغرب إلى أن يكون لها فيء ـ أي: ظل ـ من حائط المربض على قدر طوله، وذلك حيث يكون ظل كل شيء مثله."
          },
          {
            "id": 2,
            "text": "أي: لا تزالوا تصلون بهم العصر من نهاية وقت الظهر ما دامت الشمس بيضاء حية لم تصفر، وذلك في جزء من النهار يسع السير فرسخين. والضمير في «فيها» للعضو باعتبار كونه مدة."
          },
          {
            "id": 3,
            "text": "«يدفع الحاج» أي: يفيض من عرفات."
          },
          {
            "id": 4,
            "text": "أي: لا يكون الإمام موجبا لفتنة المأمومين ونفرتهم من الصلاة بالتطويل."
          }
        ]
      }
    ]
  }
}